rtl/FMA.sv
module FMA (
	input logic [31:0]  a_fp,
	input logic [31:0]  b_fp,
	input logic [31:0]  c_fp,
	output logic [31:0] out_fp,
        output logic        ready
);

	logic sign_out, largerMag;
	logic [7:0] exp_out, final_exp;
	logic [23:0] mantissa_a, mantissa_b, mantissa_c, mantissa_mul_norm, final_mantissa;
	logic [47:0] mantissa_mul_out;
	logic [24:0] sum_mants;
	
	
	always_comb begin
		mantissa_a = (a_fp == 32'b0) ? 24'b0 : {1'b1, a_fp[22:0]};
		mantissa_b = (b_fp == 32'b0) ? 24'b0 : {1'b1, b_fp[22:0]};
		mantissa_c = (c_fp == 32'b0) ? 24'b0 : {1'b1, c_fp[22:0]};
	
		sign_out = a_fp[31] ^ b_fp[31];
		exp_out = a_fp[30:23] + b_fp[30:23] - 8'h7F;
		mantissa_mul_out = mantissa_a * mantissa_b;
		mantissa_mul_norm = mantissa_mul_out[47:24];
		
		if (mantissa_mul_norm[23]) begin
			mantissa_mul_norm = mantissa_mul_norm << 1;
			
		end else if (mantissa_mul_norm[22]) begin
			mantissa_mul_norm = mantissa_mul_norm << 2;
			exp_out = exp_out - 1;
		
		end else if (mantissa_mul_norm[21]) begin
			mantissa_mul_norm = mantissa_mul_norm << 3;
			exp_out = exp_out - 2;
		end else if (mantissa_mul_norm[20]) begin
			mantissa_mul_norm = mantissa_mul_norm << 4;
			exp_out = exp_out - 3;
		
		end else if (mantissa_mul_norm[19]) begin
			mantissa_mul_norm = mantissa_mul_norm << 5;
			exp_out = exp_out - 4;
		
		end else if (mantissa_mul_norm[18]) begin
			mantissa_mul_norm = mantissa_mul_norm << 6;
			exp_out = exp_out - 5;
		
		end else if (mantissa_mul_norm[17]) begin
			mantissa_mul_norm = mantissa_mul_norm << 7;
			exp_out = exp_out - 6;
		
		end else if (mantissa_mul_norm[16]) begin
			mantissa_mul_norm = mantissa_mul_norm << 8;
			exp_out = exp_out - 7;
		
		end else if (mantissa_mul_norm[15]) begin
			mantissa_mul_norm = mantissa_mul_norm << 9;
			exp_out = exp_out - 8;
		
		end else if (mantissa_mul_norm[14]) begin
			mantissa_mul_norm = mantissa_mul_norm << 10;
			exp_out = exp_out - 9;
		
		end else if (mantissa_mul_norm[13]) begin
			mantissa_mul_norm = mantissa_mul_norm << 11;
			exp_out = exp_out - 10;
		
		end else if (mantissa_mul_norm[12]) begin
			mantissa_mul_norm = mantissa_mul_norm << 12;
			exp_out = exp_out - 11;
		
		end else if (mantissa_mul_norm[11]) begin
			mantissa_mul_norm = mantissa_mul_norm << 13;
			exp_out = exp_out - 12;
		
		end else if (mantissa_mul_norm[10]) begin
			mantissa_mul_norm = mantissa_mul_norm << 14;
			exp_out = exp_out - 13;
		
		end else if (mantissa_mul_norm[9]) begin
			mantissa_mul_norm = mantissa_mul_norm << 15;
			exp_out = exp_out - 14;
		
		end else if (mantissa_mul_norm[8]) begin
			mantissa_mul_norm = mantissa_mul_norm << 16;
			exp_out = exp_out - 15;
		
		end else if (mantissa_mul_norm[7]) begin
			mantissa_mul_norm = mantissa_mul_norm << 17;
			exp_out = exp_out - 16;
		
		end else if (mantissa_mul_norm[6]) begin
			mantissa_mul_norm = mantissa_mul_norm << 18;
			exp_out = exp_out - 17;
		
		end else if (mantissa_mul_norm[5]) begin
			mantissa_mul_norm = mantissa_mul_norm << 19;
			exp_out = exp_out - 18;
		
		end else if (mantissa_mul_norm[4]) begin
			mantissa_mul_norm = mantissa_mul_norm << 20;
			exp_out = exp_out - 19;
		
		end else if (mantissa_mul_norm[3]) begin
			mantissa_mul_norm = mantissa_mul_norm << 21;
			exp_out = exp_out - 20;
		
		end else if (mantissa_mul_norm[2]) begin
			mantissa_mul_norm = mantissa_mul_norm << 22;
			exp_out = exp_out - 21;
		
		end else if (mantissa_mul_norm[1]) begin
			mantissa_mul_norm = mantissa_mul_norm << 23;
			exp_out = exp_out - 22;
		end
		else begin
			exp_out = 8'b11111111;
		end
		exp_out = exp_out + 1;
		//out_mul = {sign_out, exp_out, mantissa_mul_norm[23:1]};
		//num1 = mul_out
		//num2 = c_fp
		// largerMag - 1: c > mul_out, 0: mul_out >= c
		mantissa_mul_norm = (a_fp == 32'b0 || b_fp == 32'b0) ? 24'b0 : {1'b1, mantissa_mul_norm[23:1]}; // reassign mantissa
		
		if(exp_out < c_fp[30:23]) begin
   			final_exp = c_fp[30:23];
  	 		mantissa_mul_norm = mantissa_mul_norm >> (final_exp - exp_out);
  	 		largerMag = 1'b1;
  	 	end else if (c_fp[30:23] < exp_out) begin
   			final_exp = exp_out;
   			mantissa_c = mantissa_c >> (final_exp - c_fp[30:23]);
   			largerMag = 1'b0;
   		end else begin
   			final_exp = exp_out;
   			if (mantissa_c > mantissa_mul_norm) begin
   				largerMag = 1'b1;
   			end else begin
   				largerMag = 1'b0;
   			end
  	 	end
		
		if ((sign_out == 1'b1) && (c_fp[31] == 1'b1)) begin // two positive so add
   			sum_mants = mantissa_c + mantissa_mul_norm;
   			sign_out = 1'b0;
   		
   			final_mantissa = sum_mants[24:1];
   	   		final_exp = final_exp+1;
  	 	end else if ((sign_out == 1'b1) && (c_fp[31] == 1'b0)) begin
  	 		sum_mants = mantissa_mul_norm - mantissa_c;
  	 		sign_out = largerMag ? 1'b1 : 1'b0;
  	 		
  	 		final_mantissa = sum_mants[23:0];
  	 		final_mantissa = sum_mants[24] ? final_mantissa * -1 : final_mantissa;
  	 	end else if ((sign_out == 1'b0) && (c_fp[31] == 1'b1)) begin
  	 		sum_mants = mantissa_c - mantissa_mul_norm;
  	 		sign_out = largerMag ? 1'b0 : 1'b1;
   		
  	 		final_mantissa = sum_mants[23:0];
  	 		final_mantissa = sum_mants[24] ? final_mantissa * -1 : final_mantissa;
  	 	end else begin
  	 		sum_mants = mantissa_c + mantissa_mul_norm;
  	 		sign_out = 1'b1;
  	 		
  	 		final_mantissa = sum_mants[24:1];
  	 		final_exp = final_exp+1;
  	 	end
  	 	
  	 	
  	 	if (final_mantissa[23]) begin
			final_mantissa = final_mantissa << 1;
			
		end else if (final_mantissa[22]) begin
			final_mantissa = final_mantissa << 2;
			final_exp = final_exp - 1;
		
		end else if (final_mantissa[21]) begin
			final_mantissa = final_mantissa << 3;
			final_exp = final_exp - 2;
		end else if (final_mantissa[20]) begin
			final_mantissa = final_mantissa << 4;
			final_exp = final_exp - 3;
		
		end else if (final_mantissa[19]) begin
			final_mantissa = final_mantissa << 5;
			final_exp = final_exp - 4;
		
		end else if (final_mantissa[18]) begin
			final_mantissa = final_mantissa << 6;
			final_exp = final_exp - 5;
		
		end else if (final_mantissa[17]) begin
			final_mantissa = final_mantissa << 7;
			final_exp = final_exp - 6;
		
		end else if (final_mantissa[16]) begin
			final_mantissa = final_mantissa << 8;
			final_exp = final_exp - 7;
		
		end else if (final_mantissa[15]) begin
			final_mantissa = final_mantissa << 9;
			final_exp = final_exp - 8;
		
		end else if (final_mantissa[14]) begin
			final_mantissa = final_mantissa << 10;
			final_exp = final_exp - 9;
		
		end else if (final_mantissa[13]) begin
			final_mantissa = final_mantissa << 11;
			final_exp = final_exp - 10;
		
		end else if (final_mantissa[12]) begin
			final_mantissa = final_mantissa << 12;
			final_exp = final_exp - 11;
		
		end else if (final_mantissa[11]) begin
			final_mantissa = final_mantissa << 13;
			final_exp = final_exp - 12;
		
		end else if (final_mantissa[10]) begin
			final_mantissa = final_mantissa << 14;
			final_exp = final_exp - 13;
		
		end else if (final_mantissa[9]) begin
			final_mantissa = final_mantissa << 15;
			final_exp = final_exp - 14;
		
		end else if (final_mantissa[8]) begin
			final_mantissa = final_mantissa << 16;
			final_exp = final_exp - 15;
		
		end else if (final_mantissa[7]) begin
			final_mantissa = final_mantissa << 17;
			final_exp = final_exp - 16;
		
		end else if (final_mantissa[6]) begin
			final_mantissa = final_mantissa << 18;
			final_exp = final_exp - 17;
		
		end else if (final_mantissa[5]) begin
			final_mantissa = final_mantissa << 19;
			final_exp = final_exp - 18;
		
		end else if (final_mantissa[4]) begin
			final_mantissa = final_mantissa << 20;
			final_exp = final_exp - 19;
		
		end else if (final_mantissa[3]) begin
			final_mantissa = final_mantissa << 21;
			final_exp = final_exp - 20;
		
		end else if (final_mantissa[2]) begin
			final_mantissa = final_mantissa << 22;
			final_exp = final_exp - 21;
		
		end else if (final_mantissa[1]) begin
			final_mantissa = final_mantissa << 23;
			final_exp = final_exp - 22;
		end
		else begin
			final_exp = final_exp - 1;
		end
	end
	
	assign out_fp = {~sign_out, final_exp, final_mantissa[23:1]};
   

endmodule

src/fmul.sv
module fmul (
	input logic [31:0] num1,
	input logic [31:0] num2,
	output logic [31:0] out_mul
);
	
	logic sign;
	logic [7:0] expF;
	logic [22:0] mantissa;
	logic [23:0] mantissa1, mantissa2;
	logic [47:0] mantissaProd;
	assign mantissa1 = {1'b1, num1[22:0]};
	assign mantissa2 = {1'b1, num2[22:0]};
	assign sign = num1[31] ^ num2[31];
	
	int i;
	
	always_comb begin
		mantissaProd = mantissa1*mantissa2;
		expF = (num1[30:23] + num2[30:23]) - 8'h7F;
		mantissa = mantissaProd[47:25];
		i = 0;
		for (i = 0; i < 23; i++) begin //do this routine a max of 23 times in case the answer is zero
			if (mantissa[22] == 1'b1) begin // if we have encountered a one we are done bc we can make the final silent bit
				i = 23; 
			end
			else begin // if we haven't encountered a one then we have to continue left shifting to find a one for the silent bit.
				mantissa = mantissa << 1;
				mantissa[0] = mantissaProd[24];
				mantissaProd = mantissaProd << 1;
				expF = expF-1;
			end
		end
		mantissa = mantissa << 1;
		expF = expF+1;
		mantissa[0] = mantissaProd[24];
		
		out_mul = {sign, expF, mantissa};
	end

endmodule

src/fadd.sv
module fadd (
	input logic [31:0] num1,
	input logic [31:0] num2,
	output logic [31:0] out_num
);
	logic largerMag, finalSign;
	logic [7:0] num1Exp, num2Exp, finalExp;
	logic [23:0] num1Mant, num2Mant, finalMant;
	logic [24:0] sumMants;
	int i;
	 
	
	always_comb begin
		finalSign = 1'b0;
		largerMag = 1'b0;
   		num1Exp = num1[30:23]; //mul
   		num2Exp = num2[30:23]; //add
   		num1Mant = {1'b1, num1[22:0]};
   		num2Mant = {1'b1, num2[22:0]};
      
   		if(num1Exp < num2Exp) begin
   			finalExp = num2Exp;
  	 		num1Mant = num1Mant >> (finalExp - num2Exp);
  	 		largerMag = 1'b1;
  	 	end else if (num2Exp < num1Exp) begin
   			finalExp = num1Exp;
   			num2Mant = num2Mant >> (finalExp - num2Exp);
   			largerMag = 1'b0;
   		end else begin
   			finalExp = num1Exp;
   			if (num2Mant > num1Mant) begin
   				largerMag = 1'b1;
   			end else begin
   				largerMag = 1'b0;
   			end
  	 	end
   	
  	 	if ((num1[31] == 1'b1) && (num2[31] == 1'b1)) begin // two positive so add
   			sumMants = num2Mant + num1Mant;
   			finalSign = 1'b0;
   		
   			finalMant = sumMants[24:1];
   	   		finalExp = finalExp+1;
  	 	end else if ((num1[31] == 1'b1) && (num2[31] == 1'b0)) begin
  	 		sumMants = num1Mant - num2Mant;
  	 		finalSign = largerMag ? 1'b1 : 1'b0;
  	 		
  	 		finalMant = sumMants[23:0];
  	 		finalMant = sumMants[24] ? finalMant * -1 : finalMant;
  	 	end else if ((num1[31] == 1'b0) && (num2[31] == 1'b1)) begin
  	 		sumMants = num2Mant - num1Mant;
  	 		finalSign = largerMag ? 1'b0 : 1'b1;
   		
  	 		finalMant = sumMants[23:0];
  	 		finalMant = sumMants[24] ? finalMant * -1 : finalMant;
  	 	end else begin
  	 		sumMants = num2Mant + num1Mant;
  	 		finalSign = 1'b1;
  	 		
  	 		finalMant = sumMants[24:1];
  	 		finalExp = finalExp+1;
  	 	end
   	
  	 	//sumMants = addMant + mulMant; //have to change sign instead of two's complementing
  	 	
//	   	$display("%b", sumMants);
   	
  	 	for (i = 0; i < 23; i++) begin //do this routine a max of 23 times in case the answer is zero
			if (finalMant[23] == 1'b1) begin // if we have encountered a one we are done bc we can make the final silent bit
				i = 23; 
			end
			else begin // if we haven't encountered a one then we have to continue left shifting to find a one for the silent bit.
				finalMant = finalMant << 1;
				finalExp = finalExp - 1;
//				$display("shifted left");
			end
  	   	end
  	   	finalMant = finalMant << 1;
  	   	//finalExp = finalExp - 1;
  	      //"rounding" denormalized values like 1e-34 (which is returned for some 0+n computations, down to zero
  	      if(num1 == 0 && num2Exp == 0) begin
  	         finalMant = 24'b0;
  	         finalExp = 8'b0;
  	      end	
	end
	
	assign out_num = {~finalSign, finalExp, finalMant[23:1]}; //need to do sign bit stuff
	
endmodule

src/PE.sv
// Implementation of one PE in the Accelerant Mesh

module PE (
           // Global clock (everything is based on one clock sadly)
           input logic         clk,
           // Switch input/out
           input logic         reset,
           input logic         load,
           input logic [3:0]   instruction,
           input logic [31:0]  a,
           input logic [31:0]  b,
           input logic [31:0]  c,
           input logic [31:0]  internal_data_in, // data sent by the switch during programming phase
           output logic [31:0] out_to_switch
           );

   // Used for Systolic FMA
   logic [31:0] internal_register;
   logic [3:0]  configuration;


   // Units:
   // 0. Fadd
   // 1. FMul
   // 2. FMA

   // Instructions:
   // 0 000 -> Fadd
   // 0 001 -> Fmul
   // 1 010 -> Systolic FMA
   // 0 011 -> Regular FMA
   
// To implement:
   // 3. FSUB
   // 4. Finv
   // 5. FReLU
   // 6. Fsqrt
   // 7. FLn
   // 8. FLT
   // 9. FLE
   // 10. FEQ
   // 11. Systolic FMA
   
   logic [31:0]       a_input_pins[5:0];
   logic [31:0]       b_input_pins[5:0];
   logic [31:0]       c_input_pins[5:0];
   logic [31:0]       out_pins[5:0];
   


   fadd fa(a_input_pins[0], b_input_pins[0], out_pins[0]);
   fmul fm(a_input_pins[1], b_input_pins[1], out_pins[1]);
   FMA systolic_fma(a_input_pins[2], b_input_pins[2], c_input_pins[2], out_pins[2]);
   FMA fma2(a_input_pins[3], b_input_pins[3], c_input_pins[3], out_pins[3]);

   always @(posedge clk) begin
      if(reset) begin
         configuration <= 0;
         internal_register <= 0;
      end
      else if(load) begin
         if(instruction != 4'b0010) begin
            configuration <= instruction;
         end
         internal_register <= internal_data_in;
      end
      else begin
         a_input_pins[configuration[2:0]] <= a;
         if (configuration[3]) begin
            b_input_pins[configuration[2:0]] <= internal_register;
         end
         else b_input_pins[configuration[2:0]] <= b;
         c_input_pins[configuration[2:0]] <= c;
         out_to_switch <= out_pins[configuration[2:0]];
      end
   end
   
   
   

   


endmodule; // PE

src/tests/waveform.vcd
$version Generated by VerilatedVcd $end
$timescale 1ps $end

 $scope module TOP $end
  $var wire 32 x a [31:0] $end
  $var wire 32 y b [31:0] $end
  $var wire 32 z c [31:0] $end
  $var wire  1 t clk $end
  $var wire  4 w instruction [3:0] $end
  $var wire 32 { internal_data_in [31:0] $end
  $var wire  1 v load $end
  $var wire 32 | out_to_switch [31:0] $end
  $var wire  1 u reset $end
  $scope module PE $end
   $var wire 32 x a [31:0] $end
   $var wire 32 % a_input_pins[0] [31:0] $end
   $var wire 32 & a_input_pins[1] [31:0] $end
   $var wire 32 ' a_input_pins[2] [31:0] $end
   $var wire 32 ( a_input_pins[3] [31:0] $end
   $var wire 32 ) a_input_pins[4] [31:0] $end
   $var wire 32 * a_input_pins[5] [31:0] $end
   $var wire 32 y b [31:0] $end
   $var wire 32 + b_input_pins[0] [31:0] $end
   $var wire 32 , b_input_pins[1] [31:0] $end
   $var wire 32 - b_input_pins[2] [31:0] $end
   $var wire 32 . b_input_pins[3] [31:0] $end
   $var wire 32 / b_input_pins[4] [31:0] $end
   $var wire 32 0 b_input_pins[5] [31:0] $end
   $var wire 32 z c [31:0] $end
   $var wire 32 1 c_input_pins[0] [31:0] $end
   $var wire 32 2 c_input_pins[1] [31:0] $end
   $var wire 32 3 c_input_pins[2] [31:0] $end
   $var wire 32 4 c_input_pins[3] [31:0] $end
   $var wire 32 5 c_input_pins[4] [31:0] $end
   $var wire 32 6 c_input_pins[5] [31:0] $end
   $var wire  1 t clk $end
   $var wire  4 $ configuration [3:0] $end
   $var wire  4 w instruction [3:0] $end
   $var wire 32 { internal_data_in [31:0] $end
   $var wire 32 # internal_register [31:0] $end
   $var wire  1 v load $end
   $var wire 32 7 out_pins[0] [31:0] $end
   $var wire 32 8 out_pins[1] [31:0] $end
   $var wire 32 9 out_pins[2] [31:0] $end
   $var wire 32 : out_pins[3] [31:0] $end
   $var wire 32 ; out_pins[4] [31:0] $end
   $var wire 32 < out_pins[5] [31:0] $end
   $var wire 32 | out_to_switch [31:0] $end
   $var wire  1 u reset $end
   $scope module fa $end
    $var wire  8 D finalExp [7:0] $end
    $var wire 24 G finalMant [23:0] $end
    $var wire  1 A finalSign $end
    $var wire 32 } i [31:0] $end
    $var wire  1 @ largerMag $end
    $var wire 32 = num1 [31:0] $end
    $var wire  8 B num1Exp [7:0] $end
    $var wire 24 E num1Mant [23:0] $end
    $var wire 32 > num2 [31:0] $end
    $var wire  8 C num2Exp [7:0] $end
    $var wire 24 F num2Mant [23:0] $end
    $var wire 32 ? out_num [31:0] $end
    $var wire 25 H sumMants [24:0] $end
   $upscope $end
   $scope module fm $end
    $var wire  8 M expF [7:0] $end
    $var wire 32 S i [31:0] $end
    $var wire 23 N mantissa [22:0] $end
    $var wire 24 O mantissa1 [23:0] $end
    $var wire 24 P mantissa2 [23:0] $end
    $var wire 48 Q mantissaProd [47:0] $end
    $var wire 32 I num1 [31:0] $end
    $var wire 32 J num2 [31:0] $end
    $var wire 32 K out_mul [31:0] $end
    $var wire  1 L sign $end
   $upscope $end
   $scope module fma2 $end
    $var wire 32 T a_fp [31:0] $end
    $var wire 32 U b_fp [31:0] $end
    $var wire 32 V c_fp [31:0] $end
    $var wire  8 Z exp_out [7:0] $end
    $var wire  8 [ final_exp [7:0] $end
    $var wire 24 ` final_mantissa [23:0] $end
    $var wire  1 Y largerMag $end
    $var wire 24 \ mantissa_a [23:0] $end
    $var wire 24 ] mantissa_b [23:0] $end
    $var wire 24 ^ mantissa_c [23:0] $end
    $var wire 24 _ mantissa_mul_norm [23:0] $end
    $var wire 48 a mantissa_mul_out [47:0] $end
    $var wire 32 W out_fp [31:0] $end
    $var wire  1 X sign_out $end
    $var wire 25 c sum_mants [24:0] $end
   $upscope $end
   $scope module systolic_fma $end
    $var wire 32 d a_fp [31:0] $end
    $var wire 32 e b_fp [31:0] $end
    $var wire 32 f c_fp [31:0] $end
    $var wire  8 j exp_out [7:0] $end
    $var wire  8 k final_exp [7:0] $end
    $var wire 24 p final_mantissa [23:0] $end
    $var wire  1 i largerMag $end
    $var wire 24 l mantissa_a [23:0] $end
    $var wire 24 m mantissa_b [23:0] $end
    $var wire 24 n mantissa_c [23:0] $end
    $var wire 24 o mantissa_mul_norm [23:0] $end
    $var wire 48 q mantissa_mul_out [47:0] $end
    $var wire 32 g out_fp [31:0] $end
    $var wire  1 h sign_out $end
    $var wire 25 s sum_mants [24:0] $end
   $upscope $end
  $upscope $end
 $upscope $end
$enddefinitions $end


#0
b00000000000000000000000000000000 #
b0000 $
b00000000000000000000000000000000 %
b00000000000000000000000000000000 &
b00000000000000000000000000000000 '
b00000000000000000000000000000000 (
b00000000000000000000000000000000 )
b00000000000000000000000000000000 *
b00000000000000000000000000000000 +
b00000000000000000000000000000000 ,
b00000000000000000000000000000000 -
b00000000000000000000000000000000 .
b00000000000000000000000000000000 /
b00000000000000000000000000000000 0
b00000000000000000000000000000000 1
b00000000000000000000000000000000 2
b00000000000000000000000000000000 3
b00000000000000000000000000000000 4
b00000000000000000000000000000000 5
b00000000000000000000000000000000 6
b00000000000000000000000000000000 7
b01000000100000000000000000000000 8
b00000000000000000000000000000000 9
b00000000000000000000000000000000 :
b00000000000000000000000000000000 ;
b00000000000000000000000000000000 <
b00000000000000000000000000000000 =
b00000000000000000000000000000000 >
b00000000000000000000000000000000 ?
0@
1A
b00000000 B
b00000000 C
b00000000 D
b100000000000000000000000 E
b100000000000000000000000 F
b000000000000000000000000 G
b1000000000000000000000000 H
b00000000000000000000000000000000 I
b00000000000000000000000000000000 J
b01000000100000000000000000000000 K
0L
b10000001 M
b00000000000000000000000 N
b100000000000000000000000 O
b100000000000000000000000 P
b100000000000000000000000000000000000000000000000 Q
b00000000000000000000000000011000 S
b00000000000000000000000000000000 T
b00000000000000000000000000000000 U
b00000000000000000000000000000000 V
b00000000000000000000000000000000 W
1X
0Y
b00000000 Z
b00000000 [
b000000000000000000000000 \
b000000000000000000000000 ]
b000000000000000000000000 ^
b000000000000000000000000 _
b000000000000000000000000 `
b000000000000000000000000000000000000000000000000 a
b0000000000000000000000000 c
b00000000000000000000000000000000 d
b00000000000000000000000000000000 e
b00000000000000000000000000000000 f
b00000000000000000000000000000000 g
1h
0i
b00000000 j
b00000000 k
b000000000000000000000000 l
b000000000000000000000000 m
b000000000000000000000000 n
b000000000000000000000000 o
b000000000000000000000000 p
b000000000000000000000000000000000000000000000000 q
b0000000000000000000000000 s
0t
0u
1v
b1010 w
b00000000000000000000000000000000 x
b00000000000000000000000000000000 y
b00000000000000000000000000000000 z
b01000010000100100011011001000110 {
b00000000000000000000000000000000 |
b00000000000000000000000000000000 }
#1
b01000010000100100011011001000110 #
b1010 $
1t
#2
0t
#3
1t
#4
0t
#5
1t
#6
0t
#7
1t
#8
0t
#9
1t
#10
0t
#11
b01000110000110011001110011011001 '
b01000010000100100011011001000110 -
b01000010000000001101100001000101 3
b01001000101011110111110000001110 9
b01000110000110011001110011011001 d
b01000010000100100011011001000110 e
b01000010000000001101100001000101 f
b01001000101011110111110000001110 g
b10010001 j
b10010001 k
b100110011001110011011001 l
b100100100011011001000110 m
b000000000000010000000110 n
b101011110111100000001000 o
b010111101111100000011100 p
b010101111011110000000100110110001010100101010110 q
b0101011110111110000001110 s
1t
0v
b01000110000110011001110011011001 x
b01000101011011100100111100001111 y
b01000010000000001101100001000101 z
#12
0t
#13
1t
b01001000101011110111110000001110 |
#14
0t
#15
1t
#16
0t
#17
1t
#18
0t
#19
1t
#20
0t
b01000000110100000000000000000000 x
b01000000010011001100110011001101 y
b01000001001000110011001100110011 z
#21
b01000000110100000000000000000000 '
b01000001001000110011001100110011 3
b01000011011101111100101101100010 9
b01000000110100000000000000000000 d
b01000001001000110011001100110011 f
b01000011011101111100101101100010 g
b10000110 j
b10000110 k
b110100000000000000000000 l
b000010100011001100110011 n
b111011011001100000110000 o
b111011111001011011000100 p
b011101101100110000011000111000000000000000000000 q
b0111101111100101101100011 s
1t
#22
0t
#23
1t
b01000011011101111100101101100010 |
#24
0t
#25
1t
#26
0t
#27
1t
#28
0t
#29
1t
#30
0t
#31
1t
#32
0t
#33
1t
#34
0t
#35
1t
#36
0t
#37
1t
#38
0t
#39
1t
#40
0t
#41
b0000 $
1t
1v
b0000 w
#42
0t
#43
1t
#44
0t
#45
1t
#46
0t
#47
1t
#48
0t
#49
1t
#50
0t
0v
#51
b01000000110100000000000000000000 %
b01000000010011001100110011001101 +
b01000001001000110011001100110011 1
b01000001000110110011001100110011 7
b01000000110100000000000000000000 =
b01000000010011001100110011001101 >
b01000001000110110011001100110011 ?
b10000001 B
b10000000 C
b10000010 D
b110100000000000000000000 E
b011001100110011001100110 F
b001101100110011001100110 G
b1001101100110011001100110 H
1t
b00000000000000000000000000000000 |
#52
0t
#53
1t
b01000001000110110011001100110011 |
